ofunctions.delayed_keyboardinterrupt-0.1.0-py3.8-nspkg.pth
ofunctions/bisection/__init__.py
ofunctions/checksums/__init__.py
ofunctions/delayed_keyboardinterrupt/__init__.py
ofunctions/file_utils/__init__.py
ofunctions/json_sanitize/__init__.py
ofunctions/logger_utils/__init__.py
ofunctions/mailer/__init__.py
ofunctions/misc/__init__.py
ofunctions/network/__init__.py
ofunctions/platform/__init__.py
ofunctions/process/__init__.py
ofunctions/random/__init__.py
ofunctions/service_control/__init__.py
ofunctions/string_handling/__init__.py
ofunctions.delayed_keyboardinterrupt-0.1.0.dist-info/LICENSE
ofunctions.delayed_keyboardinterrupt-0.1.0.dist-info/METADATA
ofunctions.delayed_keyboardinterrupt-0.1.0.dist-info/WHEEL
ofunctions.delayed_keyboardinterrupt-0.1.0.dist-info/namespace_packages.txt
ofunctions.delayed_keyboardinterrupt-0.1.0.dist-info/top_level.txt
ofunctions.delayed_keyboardinterrupt-0.1.0.dist-info/RECORD
